Metadata-Version: 2.4
Name: iflow-mcp_paperpal
Version: 0.1.0
Summary: Paperpal is a tool that helps you write literature reviews for machine learning papers.
Requires-Python: >=3.11
License-File: LICENSE
Requires-Dist: httpx>=0.28.1
Requires-Dist: mcp[cli]>=1.5.0
Requires-Dist: pydantic>=2.0.0
Dynamic: license-file
